{
  "name": "terrashroom",
  "symbol": "TERRASHROO",
  "description": "Automated mushroom-growing device. Pitched on Shark Tank S16E4. No deal. Unofficial fan tribute & parody token. Not affiliated with or endorsed by the company, its founders, or Shark Tank / ABC / Sony. Not financial advice; no promise of value.",
  "image": "https://meta.thepumptank.fun/img/s16e4p1375-terrashroom.png",
  "createdOn": "https://pump.fun",
  "website": "https://thepumptank.fun/token/s16e4p1375-terrashroom",
  "youtube": "https://www.youtube.com/watch?v=4IN04CK5jGs"
}