{
  "name": "2400 Expert",
  "symbol": "2400EXPERT",
  "description": "test prep resource for mastering the SAT test. Pitched on Shark Tank S7E15. Unofficial fan tribute & parody token. Not affiliated with or endorsed by the company, its founders, or Shark Tank / ABC / Sony. Not financial advice; no promise of value.",
  "image": "https://meta.thepumptank.fun/img/s7e15p555-2400expert.png",
  "createdOn": "https://pump.fun",
  "website": "https://thepumptank.fun/token/s7e15p555-2400expert",
  "youtube": "https://www.youtube.com/watch?v=Seth3AAqHVc"
}