{
  "name": "Loctote Industrial Bag",
  "symbol": "LOCTOTEIND",
  "description": "drawstring pack that is cut-resistant. Pitched on Shark Tank S8E22. Unofficial fan tribute & parody token. Not affiliated with or endorsed by the company, its founders, or Shark Tank / ABC / Sony. Not financial advice; no promise of value.",
  "image": "https://meta.thepumptank.fun/img/s8e22p699-loctoteindustrialbag.png",
  "createdOn": "https://pump.fun",
  "website": "https://thepumptank.fun/token/s8e22p699-loctoteindustrialbag"
}